{
  "customized": false,
  "data": {
    "provinceCheck": {
      "AREA_ID": 63000,
      "GAS_95": "N",
      "CHAI_35": "N",
      "AIPAOE98": "N",
      "CHAI_10": "N",
      "LNG": "N",
      "AIPAOE95": "N",
      "GAS_98": "N",
      "AIPAOE92": "N",
      "AREADESC_ISDISPLAY": "N",
      "USER_ID": "",
      "AREA_LEVEL": "1",
      "L_CNG": "N",
      "AREA_DESC": "油价适用于一价区（其他地市油价请以当地油站实际价格为准）",
      "CHAI_0": "N",
      "PROVINCE_ID": 63,
      "IS_DEL": "N",
      "E92": "N",
      "E95": "N",
      "GAS_89": "N",
      "ISSHOWOTHER": "Y",
      "AREA_NAME": "",
      "E98": "N",
      "CHAI_20": "N",
      "USER_NAME": "",
      "PROVINCE_NAME": "青海",
      "CHAI_ZYK": "N",
      "USER_PHONE": "",
      "CREATE_BY": "",
      "AIPAO98": "N",
      "GAS_92": "N",
      "CNG": "N",
      "AIPAO95": "N"
    },
    "area": [
      {
        "areaCheck": {
          "AREA_ID": 63003,
          "GAS_95": "Y",
          "CHAI_35": "N",
          "AIPAOE98": "N",
          "CHAI_10": "N",
          "LNG": "N",
          "AIPAOE95": "N",
          "GAS_98": "Y",
          "AIPAOE92": "N",
          "AREADESC_ISDISPLAY": "N",
          "USER_ID": "",
          "AREA_LEVEL": "2",
          "L_CNG": "N",
          "AREA_DESC": "",
          "CHAI_0": "Y",
          "PROVINCE_ID": 63,
          "IS_DEL": "N",
          "E92": "N",
          "E95": "N",
          "GAS_89": "N",
          "ISSHOWOTHER": "N",
          "AREA_NAME": "一价区",
          "E98": "N",
          "CHAI_20": "N",
          "USER_NAME": "",
          "PROVINCE_NAME": "青海",
          "CHAI_ZYK": "N",
          "USER_PHONE": "",
          "CREATE_DATE": "2023-04-17T10:26:57.000+00:00",
          "AIPAO98": "N",
          "GAS_92": "Y",
          "CNG": "N",
          "AIPAO95": "N"
        },
        "areaData": {
          "AREA_ID": 63003,
          "GAS_95": 7.98,
          "GAS_98_STATUS": 0.13,
          "GAS_98": 8.69,
          "PERIOD_ID": 96,
          "START_DATE": "2024-10-10 00:12:00",
          "CHECHAI_0": 7.06,
          "GAS_95_STATUS": 0.13,
          "CHECHAI_0_STATUS": 0.11,
          "GAS_92_STATUS": 0.11,
          "GAS_92": 7.44
        }
      },
      {
        "areaCheck": {
          "AREA_ID": 63002,
          "GAS_95": "Y",
          "CHAI_35": "N",
          "AIPAOE98": "N",
          "CHAI_10": "N",
          "LNG": "N",
          "AIPAOE95": "N",
          "GAS_98": "Y",
          "AIPAOE92": "N",
          "AREADESC_ISDISPLAY": "N",
          "USER_ID": "",
          "AREA_LEVEL": "2",
          "L_CNG": "N",
          "AREA_DESC": "",
          "CHAI_0": "Y",
          "PROVINCE_ID": 63,
          "IS_DEL": "N",
          "E92": "N",
          "E95": "N",
          "GAS_89": "N",
          "ISSHOWOTHER": "N",
          "AREA_NAME": "二价区",
          "E98": "N",
          "CHAI_20": "N",
          "USER_NAME": "",
          "PROVINCE_NAME": "青海",
          "CHAI_ZYK": "N",
          "USER_PHONE": "",
          "CREATE_DATE": "2023-04-17T10:26:27.000+00:00",
          "CREATE_BY": "wangzheng",
          "AIPAO98": "N",
          "GAS_92": "Y",
          "CNG": "N",
          "AIPAO95": "N"
        },
        "areaData": {
          "AREA_ID": 63002,
          "GAS_95": 8.07,
          "GAS_98_STATUS": 0.13,
          "GAS_98": 8.79,
          "PERIOD_ID": 96,
          "START_DATE": "2024-10-10 00:12:00",
          "CHECHAI_0": 7.16,
          "GAS_95_STATUS": 0.12,
          "CHECHAI_0_STATUS": 0.12,
          "GAS_92_STATUS": 0.11,
          "GAS_92": 7.53
        }
      },
      {
        "areaCheck": {
          "AREA_ID": 63001,
          "GAS_95": "Y",
          "CHAI_35": "N",
          "AIPAOE98": "N",
          "CHAI_10": "N",
          "LNG": "N",
          "AIPAOE95": "N",
          "GAS_98": "Y",
          "AIPAOE92": "N",
          "AREADESC_ISDISPLAY": "N",
          "USER_ID": "",
          "AREA_LEVEL": "2",
          "L_CNG": "N",
          "AREA_DESC": "",
          "CHAI_0": "Y",
          "PROVINCE_ID": 63,
          "IS_DEL": "N",
          "E92": "N",
          "E95": "N",
          "GAS_89": "N",
          "ISSHOWOTHER": "N",
          "AREA_NAME": "三价区",
          "E98": "N",
          "CHAI_20": "N",
          "USER_NAME": "",
          "PROVINCE_NAME": "青海",
          "CHAI_ZYK": "N",
          "USER_PHONE": "",
          "CREATE_DATE": "2023-04-17T10:26:06.000+00:00",
          "AIPAO98": "N",
          "GAS_92": "Y",
          "CNG": "N",
          "AIPAO95": "N"
        },
        "areaData": {
          "AREA_ID": 63001,
          "GAS_95": 8.18,
          "GAS_98_STATUS": 0.13,
          "GAS_98": 8.91,
          "PERIOD_ID": 96,
          "START_DATE": "2024-10-10 00:12:00",
          "CHECHAI_0": 7.27,
          "GAS_95_STATUS": 0.12,
          "CHECHAI_0_STATUS": 0.12,
          "GAS_92_STATUS": 0.11,
          "GAS_92": 7.63
        }
      }
    ],
    "provinceData": null
  },
  "toDay": "2024年10月20日",
  "nowTime": "2024-10-19T20:32:16.158+00:00",
  "createdAt": "2024-10-19T20:32:16.388Z"
}